paquete/__init__.py
paquete/saludos.py
paquete/setup.py
paquete/adios/__init__.py
paquete/adios/despedidas.py
paquete/hola/__init__.py
paquete/hola/saludos.py
test/__init__.py
test/test_hola.py
Mensajes_nemesis-4.1.dist-info/METADATA
Mensajes_nemesis-4.1.dist-info/WHEEL
Mensajes_nemesis-4.1.dist-info/top_level.txt
Mensajes_nemesis-4.1.dist-info/RECORD
